AniManga/Anime.py
AniManga/Hentai.py
AniManga/MAL.py
AniManga/Manga.py
AniManga/__init__.py
AniManga/helpers/__init__.py
AniManga/helpers/helpers.py
AniManga-0.1.1.dist-info/LICENSE
AniManga-0.1.1.dist-info/METADATA
AniManga-0.1.1.dist-info/WHEEL
AniManga-0.1.1.dist-info/top_level.txt
AniManga-0.1.1.dist-info/RECORD
