Metadata-Version: 2.1
Name: AniManga
Version: 0.1.1
Summary: AniManga is a python module which scrapes the web to get information on Anime, Manga (and hentai).
Home-page: UNKNOWN
Author: Siddhant Kumar
Author-email: centipedemonster@gmail.com
License: UNKNOWN
Keywords: anime,manga,hentai,nhentai,anime planet
Platform: UNKNOWN
Classifier: Development Status :: 1 - Planning
Classifier: Intended Audience :: Developers
Classifier: Programming Language :: Python :: 3
Classifier: Operating System :: Unix
Classifier: Operating System :: MacOS :: MacOS X
Classifier: Operating System :: Microsoft :: Windows
License-File: LICENSE
Requires-Dist: bs4
Requires-Dist: requests
Requires-Dist: html5lib
